[{
    "name": "Цефалотус",
    "price": 60.5,
    "discount": 0.1
}, {
    "name": "Дарлингтония",
    "price": 39.1,
    "discount": 0.2
}, {
    "name": "Венерина мухоловка",
    "price": 70.3,
    "discount": 0
}, {
    "name": "Росянка",
    "price": 41.6,
    "discount": 0.15
}, {
    "name": "Непентес",
    "price": 34.7,
    "discount": 0
}, {
    "name": "Росянка капская",
    "price": 60,
    "discount": 0.2
}, {
    "name": "Сарранцея беллолистная",
    "price": 100,
    "discount": 0.1
}, {
    "name": "Росянка Адель",
    "price": 45.5,
    "discount": 0.1
}, {
    "name": "Росянка Бурмана",
    "price": 47.8,
    "discount": 0
}, {
    "name": "Сарранцея попугайная",
    "price": 50,
    "discount": 0.1
}]